metapensiero/sphinx/autodoc_sa/__init__.py
metapensiero_sphinx_autodoc_sa-2.2.dist-info/METADATA
metapensiero_sphinx_autodoc_sa-2.2.dist-info/WHEEL
metapensiero_sphinx_autodoc_sa-2.2.dist-info/entry_points.txt
metapensiero_sphinx_autodoc_sa-2.2.dist-info/RECORD
