Metadata-Version: 2.1
Name: metapensiero.sphinx.autodoc_sa
Version: 2.2
Summary: Autodoc extension to pretty print canned SA queries
Author-Email: Lele Gaifax <lele@metapensiero.it>
License: GPL-3.0-or-later
Classifier: Development Status :: 4 - Beta
Classifier: Programming Language :: Python
Classifier: Programming Language :: Python :: 3
Classifier: Programming Language :: Python :: 3.11
Classifier: Programming Language :: Python :: 3.12
Classifier: Intended Audience :: Developers
Classifier: License :: OSI Approved :: GNU General Public License v3 or later (GPLv3+)
Classifier: Topic :: Database
Classifier: Topic :: Utilities
Classifier: Framework :: Sphinx :: Extension
Project-URL: Source, https://gitlab.com/metapensiero/metapensiero.sphinx.autodoc_sa
Project-URL: Changelog, https://gitlab.com/metapensiero/metapensiero.sphinx.autodoc_sa/-/blob/master/CHANGES.rst
Requires-Python: >=3.11
Requires-Dist: sphinx>=4
Requires-Dist: sqlalchemy
Provides-Extra: dev
Requires-Dist: build; extra == "dev"
Requires-Dist: bump-my-version; extra == "dev"
Requires-Dist: pglast; extra == "dev"
Requires-Dist: pytest; extra == "dev"
Requires-Dist: twine; extra == "dev"
